{
    "patches": [
        {
            "label": "2026-04-28_16-27-24",
            "content": "@@ -587,324 +587,8 @@\n %0A%7D%0A%0A\n-func(v *Vector) PushBack(value int)%7B%0A%09if v.capacity == v.size%7B%0A%09%09newCapacity := v.capacity * 2%0A%09%09newData := make(%5B%5Dint,newCapacity)%0A%0A%09%09for i,v := range v.data%7B%0A%09%09%09newData%5Bi%5D = v;+%0A%09%09%7D%0A%0A%09%09newData%5Bv.size%5D = value%0A%09%09v.size++%0A%09%09v.capacity = newCapacity%0A%09%09v.data = newData%0A%09%7Delse%7B%0A%09%09v.data%5Bsize%5D = value%0A%09%09v.size++%0A%09%7D%0A%0A%7D%0A\n func\n@@ -727,18 +727,16 @@\n Scan() %7B\n-%22%22\n %0A%09%09%09brea\n@@ -931,16 +931,19 @@\n it%22:%0A%09%09%09\n+// \n value, _\n@@ -972,16 +972,19 @@\n %5B1%5D)%0A%09%09%09\n+// \n v = NewV\n@@ -1014,16 +1014,19 @@\n sh%22:%0A%09%09%09\n+// \n for _, p\n@@ -1053,16 +1053,18 @@\n :%5D %7B%0A%09%09%09\n+//\n  %09value,\n@@ -1091,16 +1091,18 @@\n art)%0A%09%09%09\n+//\n  %09v.Push\n@@ -1116,16 +1116,19 @@\n lue)%0A%09%09%09\n+// \n %7D%0A%09%09case\n",
            "lines": "130"
        },
        {
            "label": "2026-04-29_15-00-39",
            "content": "@@ -725,20 +725,16 @@\n %09for i,v\n-alor\n  := rang\n@@ -764,12 +764,10 @@\n  = v\n-alor\n+;+\n %0A%09%09%7D\n@@ -864,26 +864,24 @@\n e%7B%0A%09%09v.data%5B\n-v.\n size%5D = valu\n",
            "lines": "149"
        },
        {
            "label": "2026-04-29_15-03-33",
            "content": "@@ -47,14 +47,8 @@\n gs%22%0A\n-%09%22os%22%0A\n )%0A%0At\n@@ -1051,16 +1051,18 @@\n Scan() %7B\n+%22%22\n %0A%09%09%09brea\n",
            "lines": "149"
        },
        {
            "label": "2026-04-29_15-04-08",
            "content": "@@ -53,19 +53,8 @@\n os%22%0A\n-%09%22strconv%22%0A\n )%0A%0At\n",
            "lines": "150"
        },
        {
            "label": "2026-04-29_15-04-24",
            "content": "@@ -1001,16 +1001,19 @@\n tdin)%0A%0A%09\n+// \n v := New\n",
            "lines": "151"
        },
        {
            "label": "2026-04-29_15-05-26",
            "content": "@@ -927,102 +927,8 @@\n %7D%0A%0A%7D\n-%0A%0Afunc(v *Vector) Status()%7B%0A%09var b strings.Builder%0A%0A%09b.WriteString(%22size:%22)%0A%09b.WriteString()%0A%7D\n %0Afun\n@@ -1499,16 +1499,18 @@\n us%22:%0A%09%09%09\n+//\n  fmt.Pri\n",
            "lines": "151"
        },
        {
            "label": "2026-04-29_15-09-12",
            "content": "@@ -1018,31 +1018,9 @@\n ing(\n-strconv.Itoa(v.size))%0A%09\n+)\n %0A%7D%0Af\n",
            "lines": "158"
        },
        {
            "label": "2026-04-29_15-10-30",
            "content": "@@ -949,22 +949,16 @@\n Status()\n-string\n %7B%0A%09var b\n@@ -1041,45 +1041,8 @@\n ))%0A%09\n-b.WriteRune(' ')%0A%09b.WriteString(%22%22)%0A%0A\n %0A%7D%0Af\n",
            "lines": "159"
        },
        {
            "label": "2026-04-29_15-11-28",
            "content": "@@ -1080,79 +1080,9 @@\n ng(%22\n-capacity:%22)%0A%09b.WriteString(strconv.Itoa(v.capacity))%0A%0A%09return b.String(\n+%22\n )%0A%0A%0A\n",
            "lines": "162"
        },
        {
            "label": "2026-04-29_15-12-25",
            "content": "package main\n\nimport (\n\t\"bufio\"\n\t\"fmt\"\n\t\"strings\"\n\t\"os\"\n\t\"strconv\"\n)\n\ntype Vector struct {\n\tdata     []int\n\tsize     int\n\tcapacity int\n}\n\nfunc NewVector(capacity int) *Vector {\n\treturn &Vector{\n\t\tdata:     make([]int, capacity), // nunca use len(data) ou cap(data) ou qq m\u00e9todo do go de manipula\u00e7\u00e3o de array\n\t\tsize:     0,\n\t\tcapacity: capacity,\n\t}\n}\n\n\nfunc Join(slice []int, sep string) string {\n\tif len(slice) == 0 {\n\t\treturn \"\"\n\t}\n\tvar result strings.Builder\n\tfmt.Fprintf(&result, \"%d\", slice[0])\n\tfor _, value := range slice[1:] {\n\t\tfmt.Fprintf(&result, \"%s%d\", sep, value)\n\t}\n\treturn result.String()\n}\n\nfunc(v *Vector) PushBack(value int){\n\tif v.capacity == v.size{\n\t\tnewCapacity := v.capacity * 2\n\t\tnewData := make([]int,newCapacity)\n\n\t\tfor i,valor := range v.data{\n\t\t\tnewData[i] = valor\n\t\t}\n\n\t\tnewData[v.size] = value\n\t\tv.size++\n\t\tv.capacity = newCapacity\n\t\tv.data = newData\n\t}else{\n\t\tv.data[v.size] = value\n\t\tv.size++\n\t}\n\n}\n\nfunc(v *Vector) Status()string{\n\tvar b strings.Builder\n\n\tb.WriteString(\"size:\")\n\tb.WriteString(strconv.Itoa(v.size))\n\tb.WriteRune(' ')\n\tb.WriteString(\"capacity:\")\n\tb.WriteString(strconv.Itoa(v.capacity))\n\n\treturn b.String()\n\n\n}\nfunc main() {\n\tvar line, cmd string\n\tscanner := bufio.NewScanner(os.Stdin)\n\n\tv := NewVector(0)\n\tfor {\n\t\tfmt.Print(\"$\")\n\t\tif !scanner.Scan() {\n\t\t\tbreak\n\t\t}\n\t\tline = scanner.Text()\n\t\tfmt.Println(line)\n\t\tparts := strings.Fields(line)\n\t\tif len(parts) == 0 {\n\t\t\tcontinue\n\t\t}\n\t\tcmd = parts[0]\n\n\t\tswitch cmd {\n\t\tcase \"end\":\n\t\t\treturn\n\t\tcase \"init\":\n\t\t\tvalue, _ := strconv.Atoi(parts[1])\n\t\t\tv = NewVector(value)\n\t\tcase \"push\":\n\t\t\tfor _, part := range parts[1:] {\n\t\t\t \tvalue, _ := strconv.Atoi(part)\n\t\t\t \tv.PushBack(value)\n\t\t\t}\n\t\tcase \"show\":\n\t\t\t// fmt.Println(v)\n\t\tcase \"status\":\n\t\t\t fmt.Println(v.Status())\n\t\tcase \"pop\":\n\t\t\t// err := v.PopBack()\n\t\t\t// if err != nil {\n\t\t\t// \tfmt.Println(err)\n\t\t\t// }\n\t\tcase \"insert\":\n\t\t\t// index, _ := strconv.Atoi(parts[1])\n\t\t\t// value, _ := strconv.Atoi(parts[2])\n\t\t\t// err := v.Insert(index, value)\n\t\t\t// if err != nil {\n\t\t\t// \tfmt.Println(err)\n\t\t\t// }\n\t\tcase \"erase\":\n\t\t\t// index, _ := strconv.Atoi(parts[1])\n\t\t\t// err := v.Erase(index)\n\t\t\t// if err != nil {\n\t\t\t// \tfmt.Println(err)\n\t\t\t// }\n\t\tcase \"indexOf\":\n\t\t\t// value, _ := strconv.Atoi(parts[1])\n\t\t\t// index := v.IndexOf(value)\n\t\t\t// fmt.Println(index)\n\t\tcase \"contains\":\n\t\t\t// value, _ := strconv.Atoi(parts[1])\n\t\t\t// if v.Contains(value) {\n\t\t\t// \tfmt.Println(\"true\")\n\t\t\t// } else {\n\t\t\t// \tfmt.Println(\"false\")\n\t\t\t// }\n\t\tcase \"clear\":\n\t\t\t// v.Clear()\n\t\tcase \"capacity\":\n\t\t\t// fmt.Println(v.Capacity())\n\t\tcase \"get\":\n\t\t\t// index, _ := strconv.Atoi(parts[1])\n\t\t\t// value, err := v.At(index)\n\t\t\t// if err != nil {\n\t\t\t// \tfmt.Println(err)\n\t\t\t// } else {\n\t\t\t// \tfmt.Println(value)\n\t\t\t// }\n\t\tcase \"set\":\n\t\t\t// index, _ := strconv.Atoi(parts[1])\n\t\t\t// value, _ := strconv.Atoi(parts[2])\n\t\t\t// err := v.Set(index, value)\n\t\t\t// if err != nil {\n\t\t\t// \tfmt.Println(err)\n\t\t\t// }\n\t\t\t// \n\t\tcase \"reserve\":\n\t\t\t// newCapacity, _ := strconv.Atoi(parts[1])\n\t\t\t// v.Reserve(newCapacity)\n\t\tcase \"slice\":\n\t\t\t// start, _ := strconv.Atoi(parts[1])\n\t\t\t// end, _ := strconv.Atoi(parts[2])\n\t\t\t// slice := v.Slice(start, end)\n\t\t\t// fmt.Println(slice)\n\t\tdefault:\n\t\t\tfmt.Println(\"fail: comando invalido\")\n\t\t}\n\t}\n}\n",
            "lines": "165"
        }
    ]
}